README.txt
setup.cfg
setup.py
MinificationWebHelpers.egg-info/PKG-INFO
MinificationWebHelpers.egg-info/SOURCES.txt
MinificationWebHelpers.egg-info/dependency_links.txt
MinificationWebHelpers.egg-info/not-zip-safe
MinificationWebHelpers.egg-info/requires.txt
MinificationWebHelpers.egg-info/top_level.txt
minwebhelpers/__init__.py
minwebhelpers/jsmin.py
tests/__init__.py
tests/fixtures/__init__.py