Metadata-Version: 1.0
Name: MinificationWebHelpers
Version: 0.3.6
Summary: CSS and Javascript Minification/Combination Upgrade to WebHelpers
Home-page: http://docs.fubar.si/minwebhelpers/
Author: Domen Kozar
Author-email: domen@dev.si
License: UNKNOWN
Platform: UNKNOWN
